google/cloud/servicecontrol/__init__.py
google/cloud/servicecontrol/gapic_version.py
google/cloud/servicecontrol/py.typed
google/cloud/servicecontrol_v1/__init__.py
google/cloud/servicecontrol_v1/gapic_metadata.json
google/cloud/servicecontrol_v1/gapic_version.py
google/cloud/servicecontrol_v1/py.typed
google/cloud/servicecontrol_v1/services/__init__.py
google/cloud/servicecontrol_v1/services/quota_controller/__init__.py
google/cloud/servicecontrol_v1/services/quota_controller/async_client.py
google/cloud/servicecontrol_v1/services/quota_controller/client.py
google/cloud/servicecontrol_v1/services/quota_controller/transports/__init__.py
google/cloud/servicecontrol_v1/services/quota_controller/transports/base.py
google/cloud/servicecontrol_v1/services/quota_controller/transports/grpc.py
google/cloud/servicecontrol_v1/services/quota_controller/transports/grpc_asyncio.py
google/cloud/servicecontrol_v1/services/quota_controller/transports/rest.py
google/cloud/servicecontrol_v1/services/quota_controller/transports/rest_base.py
google/cloud/servicecontrol_v1/services/service_controller/__init__.py
google/cloud/servicecontrol_v1/services/service_controller/async_client.py
google/cloud/servicecontrol_v1/services/service_controller/client.py
google/cloud/servicecontrol_v1/services/service_controller/transports/__init__.py
google/cloud/servicecontrol_v1/services/service_controller/transports/base.py
google/cloud/servicecontrol_v1/services/service_controller/transports/grpc.py
google/cloud/servicecontrol_v1/services/service_controller/transports/grpc_asyncio.py
google/cloud/servicecontrol_v1/services/service_controller/transports/rest.py
google/cloud/servicecontrol_v1/services/service_controller/transports/rest_base.py
google/cloud/servicecontrol_v1/types/__init__.py
google/cloud/servicecontrol_v1/types/check_error.py
google/cloud/servicecontrol_v1/types/distribution.py
google/cloud/servicecontrol_v1/types/http_request.py
google/cloud/servicecontrol_v1/types/log_entry.py
google_cloud_service_control-1.17.0.dist-info/licenses/LICENSE
google_cloud_service_control-1.17.0.dist-info/METADATA
google_cloud_service_control-1.17.0.dist-info/WHEEL
google_cloud_service_control-1.17.0.dist-info/top_level.txt
google_cloud_service_control-1.17.0.dist-info/RECORD
